<?xml version="1.0" encoding="UTF-8"?>
<openerp>
 <data>
    
    <record id="form_product_template" model="ir.ui.view">
      <field name="name">leakage_report.form_product_template</field>
      <field name="model">product.template</field>
      <field name="inherit_id" ref="product.product_template_form_view"/>
      <field name="arch" type="xml">
        <div name="options" position="inside">
            <div>
                <field name="leakage_method"/>
                <label for="leakage_method"/>
            </div>
        </div>
      </field>
    </record>
    
  </data>
</openerp>
